pycolormap_2d/__init__.py
pycolormap_2d/__version__.py
pycolormap_2d/colormap_2d.py
pycolormap_2d/data/bremm.npy
pycolormap_2d/data/cubediagonal.npy
pycolormap_2d/data/schumann.npy
pycolormap_2d/data/steiger.npy
pycolormap_2d/data/teulingfig2.npy
pycolormap_2d/data/ziegler.npy
pycolormap_2d-1.1.7.dist-info/licenses/LICENSE
pycolormap_2d-1.1.7.dist-info/METADATA
pycolormap_2d-1.1.7.dist-info/WHEEL
pycolormap_2d-1.1.7.dist-info/top_level.txt
pycolormap_2d-1.1.7.dist-info/RECORD
