Metadata-Version: 2.4
Name: pycolormap-2d
Version: 1.1.7
Summary: A Python package mapping 2D coordinates to colors based on different 2D color maps.
Author: Thilo Spinner
License: Apache-2.0
Project-URL: Homepage, https://github.com/spinthil/pycolormap-2d
Keywords: colormap,visualization
Classifier: Intended Audience :: Science/Research
Classifier: Intended Audience :: Education
Classifier: Programming Language :: Python :: 3.9
Classifier: Programming Language :: Python :: 3.10
Classifier: Programming Language :: Python :: 3.11
Classifier: Programming Language :: Python :: 3.12
Classifier: Programming Language :: Python :: 3.13
Requires-Python: >=3.9
License-File: LICENSE
Requires-Dist: numpy
Dynamic: license-file
